<Page xmlns="http://schemas.nativescript.org/tns.xsd">
    <StackLayout>
        <GridLayout rows="auto,*,*,*" columns="*,*" width="300" height="600">
            <StackLayout row="0" col="0" rowSpan="1" colSpan="2" style="background-color: #DDDDDD;">
                <Label text="Super Marshmallow Man" textWrap="true" /> 
                <Image src="res://supermarshmallowman" width="75" height="75" />
                <Label text="Escape from certain death in this wild adventure! Battle the forces of evil, but don't melt!" textWrap="true" />
                <Label text="On Sale! $14.99" />
            </StackLayout>
            <StackLayout row="1" col="0" style="background-color: #CCCCCC;">
                <Label text="Couch Commander" textWrap="true" /> 
                <Image src="res://couchcommander" width="75" height="75" />
                <Label text="$24.99" />
            </StackLayout>
            <StackLayout row="1" col="1" style="background-color: #EEEEEE;">
                <Label text="Mummy Madness" textWrap="true" /> 
                <Image src="res://mummymadness" width="75" height="75" />
                <Label text="$32.99" />
            </StackLayout>
            <StackLayout row="2" col="0" style="background-color: #EEEEEE;">
                <Label text="Pyro Robots" textWrap="true" /> 
                <Image src="res://pyrorobots" width="75" height="75" />
                <Label text="$19.99" />
            </StackLayout>
            <StackLayout row="2" col="1" style="background-color: #CCCCCC;">
                <Label text="Rescue Pups" textWrap="true" /> 
                <Image src="res://rescuepups" width="75" height="75" />
                <Label text="$9.99" />
            </StackLayout>
            <StackLayout row="3" col="0" style="background-color: #CCCCCC;">
                <Label text="Vampire Valkyrie" textWrap="true" /> 
                <Image src="res://vampirevalkyrie" width="75" height="75" />
                <Label text="$21.99" />
            </StackLayout>
        </GridLayout>
    </StackLayout>
</Page>